mmchallenge/__init__.py
mmchallenge/espion.png
mmchallenge-0.10.dist-info/DESCRIPTION.rst
mmchallenge-0.10.dist-info/METADATA
mmchallenge-0.10.dist-info/RECORD
mmchallenge-0.10.dist-info/WHEEL
mmchallenge-0.10.dist-info/metadata.json
mmchallenge-0.10.dist-info/top_level.txt
